nonebot_plugin_activity_tracker/__init__.py
nonebot_plugin_activity_tracker/cache.py
nonebot_plugin_activity_tracker/config.py
nonebot_plugin_activity_tracker/database.py
nonebot_plugin_activity_tracker/hooks.py
nonebot_plugin_activity_tracker/migrations/versions/b225ac5b3f67_init.py
nonebot_plugin_activity_tracker-0.1.1.dist-info/WHEEL
nonebot_plugin_activity_tracker-0.1.1.dist-info/METADATA
nonebot_plugin_activity_tracker-0.1.1.dist-info/RECORD
