Metadata-Version: 2.3
Name: nonebot-plugin-activity-tracker
Version: 0.1.1
Summary: 基于nonebot的会话活跃检测插件，只对活跃会话推送信息
Author: zifox666
Author-email: zifox666 <zifox666@gmail.com>
Requires-Dist: nonebot2>=2.4.3,<3.0.0
Requires-Dist: nonebot-plugin-uninfo>=0.9.0,<1.0.0
Requires-Dist: nonebot-plugin-alconna>=0.59.4,<1.0.0
Requires-Dist: nonebot-plugin-orm>=0.8.2,<1.0.0
Requires-Dist: aiocache>=0.12.3,<1.0.0
Requires-Python: >=3.10
Project-URL: Repository, https://github.com/zifox666/nonebot-plugin-activity-tracker
